{
  "creds": {
    "noiseKey": {
      "private": {
        "type": "Buffer",
        "data": "iH0uIkckYAJE+ti86ikmGLFR+xC6Kpx3K7uXBOPUjHs="
      },
      "public": {
        "type": "Buffer",
        "data": "r5d5lu/Bd5vDsIjmmZj9Du8uqZmeexBQc98nNFojhhU="
      }
    },
    "signedIdentityKey": {
      "private": {
        "type": "Buffer",
        "data": "+Du/z40S4QE9b9jQ5rQClMO7g5FAMAF3kJ0jQf+x814="
      },
      "public": {
        "type": "Buffer",
        "data": "SqPRh5j4bYRDVWT2MiKytVow1Y2BUWiwNkMSdt2QhTk="
      }
    },
    "signedPreKey": {
      "keyPair": {
        "private": {
          "type": "Buffer",
          "data": "gCJqjaLct9lnic2+xO4agsXfPDRTTiSF2r35gDY1JGU="
        },
        "public": {
          "type": "Buffer",
          "data": "KMNeN5HYt2MnrtNwucEL9ZzvooLr1ISV1H8tCqkzfw8="
        }
      },
      "signature": {
        "type": "Buffer",
        "data": "6hBdZrbVR9tH9ziZICHJ6VZjZB+kjdefl6yY67BSijw4fAqb//XlktplreUESnkcY+Bc4ekAjqpTgiGPmRLlgw=="
      },
      "keyId": 1
    },
    "registrationId": 239,
    "advSecretKey": "U8LMuAZX/PuIzXN5W3Oad+uLDxIUqhGTNS5nXX+hj+c=",
    "processedHistoryMessages": [
      {
        "key": {
          "remoteJid": "62895322176848@s.whatsapp.net",
          "fromMe": true,
          "id": "131D3FDF7C1A392802898C33F246ACD4"
        },
        "timestamp": 1662647975
      },
      {
        "key": {
          "remoteJid": "62895322176848@s.whatsapp.net",
          "fromMe": true,
          "id": "162F286A127ECC12EC1658F51FD47948"
        },
        "timestamp": 1662647976
      },
      {
        "key": {
          "remoteJid": "62895322176848@s.whatsapp.net",
          "fromMe": true,
          "id": "849BCC52AD5ECD98A1722A197296E084"
        },
        "timestamp": 1662648075
      }
    ],
    "nextPreKeyId": 40,
    "firstUnuploadedPreKeyId": 40,
    "accountSettings": {
      "unarchiveChats": false
    },
    "account": {
      "details": "CJD1hs4BEJn955gGGAM=",
      "accountSignature": "6t0215tIW37j2zKwLj3Y9tTlsRtqlHrMwOyvbhWD5cCfRdop/473AawCt+T58zDoO3gmXTP2zRgRRf0tDXWbCQ==",
      "deviceSignature": "793+QF5FhNwV6ruIn5e+JlR+JW/aWmNKXzQmI6NfZE89R6dFkVST1EnrCyxSsDByixtzV8/Y2huFPYHZGzpAgg=="
    },
    "me": {
      "id": "62895322176848:27@s.whatsapp.net",
      "name": "BY BOTZ DANI"
    },
    "signalIdentities": [
      {
        "identifier": {
          "name": "62895322176848:27@s.whatsapp.net",
          "deviceId": 0
        },
        "identifierKey": {
          "type": "Buffer",
          "data": "Bdp0TXARFHaKeylmCL04qBoXrybx9iiQ5BbqQXtCW8Fg"
        }
      }
    ],
    "platform": "smba",
    "lastAccountSyncTimestamp": 1662647964,
    "myAppStateKeyId": "AAAAAFG5"
  },
  "keys": {
    "preKeys": {
      "1": null,
      "2": null,
      "3": {
        "private": {
          "type": "Buffer",
          "data": "GHbmwQblIJZAkcbN9Eu+tN0zcwHzbc1Dz8FcsVJqg0I="
        },
        "public": {
          "type": "Buffer",
          "data": "bQBe5tTfVbqEke5iWsOukz4KW6ih0SnXA8eESYOe+Rg="
        }
      },
      "4": {
        "private": {
          "type": "Buffer",
          "data": "SEH3hve/Fuf+juPN5M4AGv9kj7T5lAh150WWCIytm2g="
        },
        "public": {
          "type": "Buffer",
          "data": "0LT9RsL6P2m7I/mvIiwyT8PBX85UI7NW1AByHFVBbSs="
        }
      },
      "5": {
        "private": {
          "type": "Buffer",
          "data": "KFa0r84P6x1dlST5nKw/jGMsCLYxJIJUHnazAJpsWVw="
        },
        "public": {
          "type": "Buffer",
          "data": "V2Ea42qN3Lg8x11kzWG4P/zeCgIqVOBrtbd/x3vP3F8="
        }
      },
      "6": {
        "private": {
          "type": "Buffer",
          "data": "kPQ9aYOHOgAM0yIrhqllY7gOdvF3v20os152Gp/DBV8="
        },
        "public": {
          "type": "Buffer",
          "data": "Um2hsE6oCaDDC2IduXzW6bWqr5yBDef1GR8edrDltmA="
        }
      },
      "7": {
        "private": {
          "type": "Buffer",
          "data": "qJsxYA7dEWYM/TMSvSe56dicJE3jLiie5gqunJbc/mA="
        },
        "public": {
          "type": "Buffer",
          "data": "UgrfOF6vMWNCvDJmXMC0Vt3UjuwdOspi8eX3MPKckXA="
        }
      },
      "8": {
        "private": {
          "type": "Buffer",
          "data": "QK2OmDSoEYM1uC6muA6k+13i9cLxAhvW7wZt5e/+iEE="
        },
        "public": {
          "type": "Buffer",
          "data": "87NcvOyWS/UlvzQPzjkHsT76CWDdQmUOo3GZVqloBCQ="
        }
      },
      "9": {
        "private": {
          "type": "Buffer",
          "data": "AJfp2snM9sxVtnVRwSJRS0rxIjJNjjOSRcA0wdzTY38="
        },
        "public": {
          "type": "Buffer",
          "data": "uFMXcmT42hPoukeB+l9AQUuNF6pWKNiu/J/L17CtQH0="
        }
      },
      "10": null,
      "11": null,
      "12": {
        "private": {
          "type": "Buffer",
          "data": "YN2tiJzrmzJwj4BAPJ6cjCNahAvlgLV91FB0R8zcGXg="
        },
        "public": {
          "type": "Buffer",
          "data": "ROWtlJMhd8+viQbcK6KcBWpmewzUyFwSfLwzCw+Knlk="
        }
      },
      "13": {
        "private": {
          "type": "Buffer",
          "data": "mPaSwp9yvZxIOk1SXYV///9O04grj7doiLQxjNRQS1w="
        },
        "public": {
          "type": "Buffer",
          "data": "RGkml4N3b6KMDaXFc2pJ7EO6BZsoqH6XSWc+FHcskyo="
        }
      },
      "14": null,
      "15": {
        "private": {
          "type": "Buffer",
          "data": "CMqgShu07T8ic29km81C6NHcuGxP/3WfEMbC1iuZc2s="
        },
        "public": {
          "type": "Buffer",
          "data": "fkkN7vO3CvJ32d10Dvl/saj33g9q6hNOC6j0QZ1mYD0="
        }
      },
      "16": {
        "private": {
          "type": "Buffer",
          "data": "WFjAWrieEJ4+mzCIM46p1PTWbU0NuW4Y1NJ3c+SY6F4="
        },
        "public": {
          "type": "Buffer",
          "data": "5mZMlhpL6RtuZQv2IWZ828q7Q/mHZOcJw8Nn7RoElBw="
        }
      },
      "17": {
        "private": {
          "type": "Buffer",
          "data": "MKcPUrV5b9Pc2A8mjxi/2AxOtljhAL7KYkmJXYq+SkI="
        },
        "public": {
          "type": "Buffer",
          "data": "040kAMKUXRaRhwLQPFmJngVp/LYzuGNw8sM71sdKCBU="
        }
      },
      "18": {
        "private": {
          "type": "Buffer",
          "data": "oPzT9Ob+w/sP41z9VZ5gYyu5xEfaz0tMk/TWQ1hYoWI="
        },
        "public": {
          "type": "Buffer",
          "data": "6r3JhWpI4J92Wd9L7WIo15umwxgoc0cBlQ+BQ6n+UU0="
        }
      },
      "19": null,
      "20": {
        "private": {
          "type": "Buffer",
          "data": "QPxN52+tnEKZINKFnId5GN9tWHgy8TpbwCOBxuf0V2o="
        },
        "public": {
          "type": "Buffer",
          "data": "J15mNwxqeDXrEp/zRY2BJlzwaxV2cKfN/nGWL96WZCk="
        }
      },
      "21": {
        "private": {
          "type": "Buffer",
          "data": "ABNOE0zeI7iBHE4NHN89sI0a8ug5Q2ZhA8oa01wEqFQ="
        },
        "public": {
          "type": "Buffer",
          "data": "BFPhw8BmQbj18ejCdRIw9VMwkqfPK1U8jHxUtN6E20k="
        }
      },
      "22": {
        "private": {
          "type": "Buffer",
          "data": "8LZrcO6MZigTJknQvfZXh/G97A4cPWZhn7cYFq2lgV4="
        },
        "public": {
          "type": "Buffer",
          "data": "/+mFhRbuk8sz5kLAf8genCfC177JWCbU6mHDKQducks="
        }
      },
      "23": {
        "private": {
          "type": "Buffer",
          "data": "wGT0HcScjRNZtRh6Fw5ZbDVYxJpOWhrAfzACzSWkX1g="
        },
        "public": {
          "type": "Buffer",
          "data": "WK7Lu3VhcFnOt/sdC0MesO/pHA0/HO/N1FrMex5TXVQ="
        }
      },
      "24": {
        "private": {
          "type": "Buffer",
          "data": "GFIlplRAmN/vnFlHMVIApAKZRcBay3qyqixR0/eZUWc="
        },
        "public": {
          "type": "Buffer",
          "data": "iUQ8Ofhn8PshP31TSmtGzoAn2ze/UaceOF2sjn+ETBU="
        }
      },
      "25": {
        "private": {
          "type": "Buffer",
          "data": "ALUhWBH+1bKmhvvrrT1V/GlMXbZ4qwaAcJaKsPibU2k="
        },
        "public": {
          "type": "Buffer",
          "data": "auaztFLSQMye9UdsjiXRT+jcWnUdpKxMBQLcA/d/NRo="
        }
      },
      "26": {
        "private": {
          "type": "Buffer",
          "data": "CIBzbGzEtNc3q8lQR5wnSO8NBNueIIDLF5UdDKFc+mE="
        },
        "public": {
          "type": "Buffer",
          "data": "0/RSpxMWikE0CaPNS1xIjWuluLv6whr+MXYwI+VPxFE="
        }
      },
      "27": null,
      "28": {
        "private": {
          "type": "Buffer",
          "data": "yG9/4DkXpP3TNC33iowFJZR7fN66yBE/fQsfB/cxH0o="
        },
        "public": {
          "type": "Buffer",
          "data": "TLGezLk5r4IJ2oBePAk8KLTmaY334M+aK10UhC04dEc="
        }
      },
      "29": {
        "private": {
          "type": "Buffer",
          "data": "uOXlTZ7vu4GlvvHi8b3YivwB+e54OzFGMS8RSzIPuWg="
        },
        "public": {
          "type": "Buffer",
          "data": "HualZ70NheM4hKnpXIfc8/FdMCpvHOnxbMvUeJJdYyU="
        }
      },
      "30": {
        "private": {
          "type": "Buffer",
          "data": "cCavRkb4HCvoigMA7/4GJbdHYOdjtwu2fWaVqYaBEWg="
        },
        "public": {
          "type": "Buffer",
          "data": "LMHalpZAxk6aW6jwNWGVUvzEvO+IibaSgRFCjoRupTs="
        }
      },
      "31": {
        "private": {
          "type": "Buffer",
          "data": "QHBzRmd1LeWjAOeKiuVB/SHYdXg1QXPw2rX9j30XRV4="
        },
        "public": {
          "type": "Buffer",
          "data": "ulm2fbbFA7LUFSpXDepAYswUklXj9J9iKAOUalQSTSU="
        }
      },
      "32": {
        "private": {
          "type": "Buffer",
          "data": "uAkmX1X31SvbliFX3PS6gABlu9mqNjCmBfiZTQPAplk="
        },
        "public": {
          "type": "Buffer",
          "data": "mRdVhA++RHB7zWs8BAIE7TLgEGOeALtK5nxrFDb8ZQU="
        }
      },
      "33": {
        "private": {
          "type": "Buffer",
          "data": "iLBH1FmBCOBO8QBd/csKtanUT7KxHso1Uxukjs1E6Vs="
        },
        "public": {
          "type": "Buffer",
          "data": "/QZt1DiV1OTEJv6sRMWmqL+Re65Xo0nzJlIDJWNLl2s="
        }
      },
      "34": {
        "private": {
          "type": "Buffer",
          "data": "aCb4cKyBqYSRUdoTYHULzm0eyG5m0bNgbN/8PJmJv3I="
        },
        "public": {
          "type": "Buffer",
          "data": "yJGdU5UTfCv5T3/H07TfPZ/O+Seosm8Tn6JoiF5GL0U="
        }
      },
      "35": {
        "private": {
          "type": "Buffer",
          "data": "mHEphhv18CnwkkFHEI5Z6AM81nA7E260iljPkQA1JGs="
        },
        "public": {
          "type": "Buffer",
          "data": "WXUrq28AfBX3Gj7BJMrBmicBd3dES7FSHQM5cdS8aSA="
        }
      },
      "36": {
        "private": {
          "type": "Buffer",
          "data": "yGWN3uDZ9GnVU2HuwDSA7vKm91e9NQRuUvnPD67JJ38="
        },
        "public": {
          "type": "Buffer",
          "data": "Ln5GOdB8ryhEaVvrv9L26dBuONOO5xDOu/K5yoaPRFU="
        }
      },
      "37": {
        "private": {
          "type": "Buffer",
          "data": "AICphkkwXDtC+G7XqCL8CTyW3HKDqcRmRRhKkH5kTH8="
        },
        "public": {
          "type": "Buffer",
          "data": "80OiR4omzc4N6JF8ivrL6fWTFxQf2m8unaibclO25h0="
        }
      },
      "38": {
        "private": {
          "type": "Buffer",
          "data": "qEggCEN2OD/fWOaOD+K9dmFCPlp9F8hr5Ds3nOFKZUM="
        },
        "public": {
          "type": "Buffer",
          "data": "zvvQ52dsOhKqQye8S/JO7C5jVCRjipOElxNGlzux1ks="
        }
      },
      "39": {
        "private": {
          "type": "Buffer",
          "data": "8H0PaF3FxINRhiRvOO2tPYxjDjsf3x6mAZXtjYjTREM="
        },
        "public": {
          "type": "Buffer",
          "data": "cIEcrT9wOM1ETi1GbqgYN7vuDSxn13gm8dJ+0y3JZlU="
        }
      }
    },
    "sessions": {
      "62895322176848.0": {
        "_sessions": {
          "BcLilxs6A4YXVqujJSyIkthdp/5LmT0Vvtm2XzuMN1MP": {
            "registrationId": 412022809,
            "currentRatchet": {
              "ephemeralKeyPair": {
                "pubKey": "BZhZgTyLASmRtQhNDi5D+3FVHCSc5CqOVkN7T36/gCF3",
                "privKey": "sPMy2kdQWDZ+/YHSml/8XC+6ofYEN224gH/aOEE3fVk="
              },
              "lastRemoteEphemeralKey": "BdztpdpPiRFNXvxCtmySbAIsNvV4OZv02qpNUIDKI2Y7",
              "previousCounter": 0,
              "rootKey": "5zzIh+MpNsP/1oq9iTCTrMzByHsVn7ud5BTgOq2U8gQ="
            },
            "indexInfo": {
              "baseKey": "BcLilxs6A4YXVqujJSyIkthdp/5LmT0Vvtm2XzuMN1MP",
              "baseKeyType": 2,
              "closed": -1,
              "used": 1662648125102,
              "created": 1662647965565,
              "remoteIdentityKey": "Bdp0TXARFHaKeylmCL04qBoXrybx9iiQ5BbqQXtCW8Fg"
            },
            "_chains": {
              "BcOadHhKJ+Slw+Eh1rd9hXt+30sA9ivB3OaZqkzbpJo+": {
                "chainKey": {
                  "counter": 5
                },
                "chainType": 2,
                "messageKeys": {}
              },
              "BdztpdpPiRFNXvxCtmySbAIsNvV4OZv02qpNUIDKI2Y7": {
                "chainKey": {
                  "counter": 1,
                  "key": "6EAiT+8W23QshjTtd5mdWin8UneS9guMk5TcPjd0pJc="
                },
                "chainType": 2,
                "messageKeys": {}
              },
              "BZhZgTyLASmRtQhNDi5D+3FVHCSc5CqOVkN7T36/gCF3": {
                "chainKey": {
                  "counter": -1,
                  "key": "q+djSgwZoED8kS8NNKEF7CHGbeQGUU4pgxUKrs9jBhA="
                },
                "chainType": 1,
                "messageKeys": {}
              }
            }
          }
        },
        "version": "v1"
      },
      "6281398750388.0": {
        "_sessions": {
          "BSW2Uufxb/1Rw/46GFhbbeL8cNWOiCxVuh69vO5gtBwq": {
            "registrationId": 2080828585,
            "currentRatchet": {
              "ephemeralKeyPair": {
                "pubKey": "Bdj4IKsxXUMSMJH/LdjQPDaLQHv0b6y2F/AhJgo7NvB1",
                "privKey": "WGYgjbBbfYFKtFPYlTcYCobOILzcO0BagdlLo5/pjWo="
              },
              "lastRemoteEphemeralKey": "Bc9ZP2B2Vk/PNF6IK4nddDc0xONCK6cSHmQP4c948oYp",
              "previousCounter": 0,
              "rootKey": "sToaYgNMj3zLqgY7+hRSDAW7aFvdv45nmze+NjDaz0E="
            },
            "indexInfo": {
              "baseKey": "BSW2Uufxb/1Rw/46GFhbbeL8cNWOiCxVuh69vO5gtBwq",
              "baseKeyType": 2,
              "closed": -1,
              "used": 1662647975824,
              "created": 1662647975824,
              "remoteIdentityKey": "Bf2pEg3YnbpVOr6wflyvGIREJPgFWXdWNpSchkYhVk5c"
            },
            "_chains": {
              "Bc9ZP2B2Vk/PNF6IK4nddDc0xONCK6cSHmQP4c948oYp": {
                "chainKey": {
                  "counter": 0,
                  "key": "SccdR6Nd5H5JMPT8X+2JMxf1SdwAIzQBAWqIolg97xE="
                },
                "chainType": 2,
                "messageKeys": {}
              },
              "Bdj4IKsxXUMSMJH/LdjQPDaLQHv0b6y2F/AhJgo7NvB1": {
                "chainKey": {
                  "counter": -1,
                  "key": "RGgafwQ0otEwV3mqdPHKXqVOcamTDZpMjKE1eE63exI="
                },
                "chainType": 1,
                "messageKeys": {}
              }
            }
          }
        },
        "version": "v1"
      },
      "6289519595897.0": {
        "_sessions": {
          "BUUGi0at6Y8/ml8OJvNvBaITbRlf+XQSdnz+qSXDKs1p": {
            "registrationId": 1636270382,
            "currentRatchet": {
              "ephemeralKeyPair": {
                "pubKey": "BUlP8M5C/CJrCSmDcpEa36PJfyYVea0GE2op77FsvT4u",
                "privKey": "CNRXUzUgxTLlDlW2Qmnd0Pr0f9yzPkQ+ehZJfz6bkkA="
              },
              "lastRemoteEphemeralKey": "Bcipx/LMCSiu5itMkhL4i5zA5RPLoRjz+edli5qeeNwK",
              "previousCounter": 0,
              "rootKey": "MZJ8FGFkklHoCh+S1I+CJMeqnrMT5GP5Z7PoemH1NC8="
            },
            "indexInfo": {
              "baseKey": "BUUGi0at6Y8/ml8OJvNvBaITbRlf+XQSdnz+qSXDKs1p",
              "baseKeyType": 2,
              "closed": -1,
              "used": 1662647981495,
              "created": 1662647981495,
              "remoteIdentityKey": "Bets1bAWXM+YOksA4o1MW87TJbq3rUYCaiiaecgj9s8F"
            },
            "_chains": {
              "Bcipx/LMCSiu5itMkhL4i5zA5RPLoRjz+edli5qeeNwK": {
                "chainKey": {
                  "counter": 1,
                  "key": "6UH9+dSVTimuaeRz+7LQEpyV5AwUb8gDteZ0SNoJfAw="
                },
                "chainType": 2,
                "messageKeys": {}
              },
              "BUlP8M5C/CJrCSmDcpEa36PJfyYVea0GE2op77FsvT4u": {
                "chainKey": {
                  "counter": -1,
                  "key": "K+sTrsAUinyU+2SubEPogFY0eLSpVbahcBn2SW+xjAI="
                },
                "chainType": 1,
                "messageKeys": {}
              }
            }
          }
        },
        "version": "v1"
      },
      "6282331660134.0": {
        "_sessions": {
          "BWg3M/WzdbLN8dooHkGZmlaP6nHGLXrrBA7w3CcpTq8x": {
            "registrationId": 68345988,
            "currentRatchet": {
              "ephemeralKeyPair": {
                "pubKey": "BaMmrkY9KkRUbGkge0MHLnUO6v3arTJaESm2GFBQWJYS",
                "privKey": "kFjyge1eUQsTQ8/3paaoHW5PiTUMzApn2xF/HgL+zGw="
              },
              "lastRemoteEphemeralKey": "BeN0ovrDL31f5+33UEatzk4yy3p8by1Se0MJQXV0c/BI",
              "previousCounter": 0,
              "rootKey": "uROBqiyUtU4/8N9/U5z/wC2oeMs5PxeceQiot2rf9Fs="
            },
            "indexInfo": {
              "baseKey": "BWg3M/WzdbLN8dooHkGZmlaP6nHGLXrrBA7w3CcpTq8x",
              "baseKeyType": 2,
              "closed": -1,
              "used": 1662647998283,
              "created": 1662647998283,
              "remoteIdentityKey": "BQfwl6txPLCjF2Le3C+pBqULVWi1bCtZAFBB5XiV0BMm"
            },
            "_chains": {
              "BeN0ovrDL31f5+33UEatzk4yy3p8by1Se0MJQXV0c/BI": {
                "chainKey": {
                  "counter": 0,
                  "key": "04/AsTHrBdXS/aJhQC+qZHeS7YEMAH3hujrDtIBzmsg="
                },
                "chainType": 2,
                "messageKeys": {}
              },
              "BaMmrkY9KkRUbGkge0MHLnUO6v3arTJaESm2GFBQWJYS": {
                "chainKey": {
                  "counter": -1,
                  "key": "JlxgdXwsVXwLFTkdGwPEV6sHofLwmDUt9ZmQGO96lbM="
                },
                "chainType": 1,
                "messageKeys": {}
              }
            }
          }
        },
        "version": "v1"
      },
      "62882007294963:2.0": {
        "_sessions": {
          "BVTHaFy9HKrmjS7AotnLQcCR4PhLLspCHfGWInYzS15S": {
            "registrationId": 236,
            "currentRatchet": {
              "ephemeralKeyPair": {
                "pubKey": "BT7QWUULwIykNruqqfv0fGAXKTnM1JD1ajFGC1shpSxI",
                "privKey": "mIh7hbXGwzwtGnNedV2yt2fvwHJoxWuOq1URX5pIy3c="
              },
              "lastRemoteEphemeralKey": "BUL1sXWgmJReY2O54WUi5XOP9PjtxyAzJvfgOIs8KSwb",
              "previousCounter": 0,
              "rootKey": "4WCOSAYa/Jt2hKlVwNUblKp3u0FVGf5Xn0vdQZi97fA="
            },
            "indexInfo": {
              "baseKey": "BVTHaFy9HKrmjS7AotnLQcCR4PhLLspCHfGWInYzS15S",
              "baseKeyType": 2,
              "closed": -1,
              "used": 1662648027308,
              "created": 1662648027308,
              "remoteIdentityKey": "BZn44qT8rV2ltgk+QvvhoB0gWN+hULqV08LFPvlDb7hO"
            },
            "_chains": {
              "BUL1sXWgmJReY2O54WUi5XOP9PjtxyAzJvfgOIs8KSwb": {
                "chainKey": {
                  "counter": 0,
                  "key": "GfQeOqhlHjEwyIOBmDUnofJ3JXQx+vTrIH/D2dU/W1w="
                },
                "chainType": 2,
                "messageKeys": {}
              },
              "BT7QWUULwIykNruqqfv0fGAXKTnM1JD1ajFGC1shpSxI": {
                "chainKey": {
                  "counter": -1,
                  "key": "Gy2pG7VTO79d9Vit0xbyzd1ZN7T1TfGZpCN6S9UN2As="
                },
                "chainType": 1,
                "messageKeys": {}
              }
            }
          }
        },
        "version": "v1"
      },
      "6281234089882.0": {
        "_sessions": {
          "BSBQtpJiTl1jjEjeRpX04RmxTAysW/W8Ua9LG1HTa/om": {
            "registrationId": 2112127824,
            "currentRatchet": {
              "ephemeralKeyPair": {
                "pubKey": "BTWe3fZ+Hn/5q40CsLhZBFko+iGFiQQC0c7X1KcNapw8",
                "privKey": "4FUGR/HnfdaHVIG3AADsz3s8W2mY1YCZL/+rTY+w5Vk="
              },
              "lastRemoteEphemeralKey": "BcvHrPnJO9P5mSWcZBylLHnw2qZ0B9auVoxJ+KONC6d4",
              "previousCounter": 0,
              "rootKey": "2lsQ8FVrfPK7/Cw/m1aP0sYqkmjLHCd1k+g5827nZI0="
            },
            "indexInfo": {
              "baseKey": "BSBQtpJiTl1jjEjeRpX04RmxTAysW/W8Ua9LG1HTa/om",
              "baseKeyType": 2,
              "closed": -1,
              "used": 1662648125175,
              "created": 1662648053685,
              "remoteIdentityKey": "BZqB6e/8REj0GFCVverrvBxHe7qjExVFT+WskHOgSN43"
            },
            "_chains": {
              "BYSMsiBwiuq5/Y8hU/izeCSU2UXQ6w101ZmFX9I5nMJa": {
                "chainKey": {
                  "counter": 0
                },
                "chainType": 2,
                "messageKeys": {}
              },
              "BcvHrPnJO9P5mSWcZBylLHnw2qZ0B9auVoxJ+KONC6d4": {
                "chainKey": {
                  "counter": 0,
                  "key": "QEO0tTYecLLuehpDzTjuquSBnTGd40QmOEp/zOsuGvI="
                },
                "chainType": 2,
                "messageKeys": {}
              },
              "BTWe3fZ+Hn/5q40CsLhZBFko+iGFiQQC0c7X1KcNapw8": {
                "chainKey": {
                  "counter": -1,
                  "key": "rWv5SmU9/2X2NXK3/leLV+j7YgMsFihoBJkQ3z+jz8c="
                },
                "chainType": 1,
                "messageKeys": {}
              }
            }
          }
        },
        "version": "v1"
      },
      "62895322176848:25.0": {
        "_sessions": {
          "BegVp4D8mC3Fm02R9nHNaYPj8NbN+fBiDXnUS1On66tH": {
            "registrationId": 131,
            "currentRatchet": {
              "ephemeralKeyPair": {
                "pubKey": "BTQP48qrZ7tccFktEx691Tp4T4sAYa/eNhU1Rr3Fa/ZL",
                "privKey": "CIy3NtmXjoMVmKuQBonvqyskCYQmH8fk/drNP9bOmFg="
              },
              "lastRemoteEphemeralKey": "BUzgpCKN9hmtY6DN3W9iDAs6isNqmVaFW+FB+RQUNRs/",
              "previousCounter": 0,
              "rootKey": "jHxWAkHoxFqNcJmSJeJwvIwOoN7zEYveUUi4h4TZAQc="
            },
            "indexInfo": {
              "baseKey": "BegVp4D8mC3Fm02R9nHNaYPj8NbN+fBiDXnUS1On66tH",
              "baseKeyType": 1,
              "closed": -1,
              "used": 1662648056614,
              "created": 1662648056614,
              "remoteIdentityKey": "BTHVMiIAW9Kd4GL84Wk61mRXz1kR4s3VK2+1WVeThapx"
            },
            "_chains": {
              "BTQP48qrZ7tccFktEx691Tp4T4sAYa/eNhU1Rr3Fa/ZL": {
                "chainKey": {
                  "counter": 0,
                  "key": "o2naNxJMMPLiA1RNqp2r4ie+rqsv/vO50TH1BNjyJUA="
                },
                "chainType": 1,
                "messageKeys": {}
              }
            },
            "pendingPreKey": {
              "signedKeyId": 1,
              "baseKey": "BegVp4D8mC3Fm02R9nHNaYPj8NbN+fBiDXnUS1On66tH",
              "preKeyId": 109
            }
          }
        },
        "version": "v1"
      },
      "62895322176848:26.0": {
        "_sessions": {
          "BSPDBE7elDbQws5b+m3iKXVx5098v9492EZLQ7qJUCIG": {
            "registrationId": 200,
            "currentRatchet": {
              "ephemeralKeyPair": {
                "pubKey": "BfwlZvXsrBNHfqniHP/7XUG1rZQ6Rdy8w4e+0nqjSgQE",
                "privKey": "YHmzAPQ7Brru9ahAAEaM7j/OrzSgK4sPyi8uyAeZinI="
              },
              "lastRemoteEphemeralKey": "BQqtFiSY4bOVvTlDsk1GhR5pFnXctvAOFjxT8Xj3seJJ",
              "previousCounter": 0,
              "rootKey": "79KJiRd3NeRkeKBthV3JyWuUNpeonE1KEvg5/nbeXD4="
            },
            "indexInfo": {
              "baseKey": "BSPDBE7elDbQws5b+m3iKXVx5098v9492EZLQ7qJUCIG",
              "baseKeyType": 1,
              "closed": -1,
              "used": 1662648056628,
              "created": 1662648056628,
              "remoteIdentityKey": "BXK14fkiPq224y1oOuAlSaQD1riOlK+ShGhJ9U0gsKMY"
            },
            "_chains": {
              "BfwlZvXsrBNHfqniHP/7XUG1rZQ6Rdy8w4e+0nqjSgQE": {
                "chainKey": {
                  "counter": 0,
                  "key": "m9oTZ7AH2culKHE6WzyYcpHpgAvmc/g2zMtjnbxAl6Q="
                },
                "chainType": 1,
                "messageKeys": {}
              }
            },
            "pendingPreKey": {
              "signedKeyId": 1,
              "baseKey": "BSPDBE7elDbQws5b+m3iKXVx5098v9492EZLQ7qJUCIG",
              "preKeyId": 22
            }
          }
        },
        "version": "v1"
      },
      "6281334961360:46.0": {
        "_sessions": {
          "BUIuiU1Cgm6VTJYAActMsiZF+83EtfWxoww+miVLTYJV": {
            "registrationId": 84,
            "currentRatchet": {
              "ephemeralKeyPair": {
                "pubKey": "BVu3H7Omw8ToXaE8dDiwjEqgnayjOrmu/tWPJ1SiwyEv",
                "privKey": "SE6q7klWCrdFhOO8NNGJy5mu09/b29NMfa96UW0JIms="
              },
              "lastRemoteEphemeralKey": "BQgUUaVsa2VYdRVszXDKk4SRmq31pO8PeiaL2bo9us4q",
              "previousCounter": 0,
              "rootKey": "y78o0Ke5UgopsUcCPK4zCgwNLiHorigq03vbfqOWGBE="
            },
            "indexInfo": {
              "baseKey": "BUIuiU1Cgm6VTJYAActMsiZF+83EtfWxoww+miVLTYJV",
              "baseKeyType": 2,
              "closed": -1,
              "used": 1662648107177,
              "created": 1662648107177,
              "remoteIdentityKey": "BaRorHkBnuDhxZGuJy6Blyqd2iI3IRRfLoTasNAsBVBj"
            },
            "_chains": {
              "BQgUUaVsa2VYdRVszXDKk4SRmq31pO8PeiaL2bo9us4q": {
                "chainKey": {
                  "counter": 0,
                  "key": "BTa1qyK1gEnX3bLpZbfEbOuQ937PbGqDbzl01lAaOYA="
                },
                "chainType": 2,
                "messageKeys": {}
              },
              "BVu3H7Omw8ToXaE8dDiwjEqgnayjOrmu/tWPJ1SiwyEv": {
                "chainKey": {
                  "counter": -1,
                  "key": "W2IydgXSWd6JIViAxW6MZwJaOfGXIv61U18C4954MtI="
                },
                "chainType": 1,
                "messageKeys": {}
              }
            }
          }
        },
        "version": "v1"
      }
    },
    "appStateSyncKeys": {
      "AAAAAFG3": {
        "keyData": "2xxcujw4SYwRy+CguD/O1uprwZ7LRvPN2gP8tCalHc4=",
        "fingerprint": {
          "rawId": 432126606,
          "currentIndex": 1,
          "deviceIndexes": [
            0,
            1
          ]
        },
        "timestamp": "1662389877740"
      },
      "AAAAAFG+": {
        "keyData": "rqerz4kIVFe5GObE8R6lkHciUiRjUoExGgKmiEN0Xcg=",
        "fingerprint": {
          "rawId": 432126607,
          "currentIndex": 6,
          "deviceIndexes": [
            0,
            1
          ]
        },
        "timestamp": "1662627691345"
      },
      "AAAAAFG/": {
        "keyData": "t34RCPOHq7DABiBORaSwck6eUd7RoyIzKUbc67wrZZc=",
        "fingerprint": {
          "rawId": 432126608,
          "currentIndex": 1,
          "deviceIndexes": [
            0,
            1
          ]
        },
        "timestamp": "1662632051171"
      },
      "AAAAAFG8": {
        "keyData": "SGHDyMTEhyAcwL7+fFrjhwS91q96SpkBaiJ75prnQW4=",
        "fingerprint": {
          "rawId": 432126607,
          "currentIndex": 6,
          "deviceIndexes": [
            0,
            1,
            2,
            6
          ]
        },
        "timestamp": "0"
      },
      "AAAAAFG9": {
        "keyData": "XgU4Y7l3AG27MFvgNO69qFwGKsazLNlpRBGr6I94L7E=",
        "fingerprint": {
          "rawId": 432126607,
          "currentIndex": 6,
          "deviceIndexes": [
            0,
            1,
            2
          ]
        },
        "timestamp": "1662627687351"
      },
      "AAAAAFG6": {
        "keyData": "dUv7aG8VMWyVX1PCCULBCbyAbJOk1vYagxs+YL21dIM=",
        "fingerprint": {
          "rawId": 432126606,
          "currentIndex": 7,
          "deviceIndexes": [
            0,
            2,
            7
          ]
        },
        "timestamp": "1662538811762"
      },
      "AAAAAFG7": {
        "keyData": "T7hnerBOksHP2kb9MkbJE86zaNLVLqnY6R0IyUVkPpA=",
        "fingerprint": {
          "rawId": 432126606,
          "currentIndex": 8,
          "deviceIndexes": [
            0,
            7
          ]
        },
        "timestamp": "1662539037233"
      },
      "AAAAAFG4": {
        "keyData": "dm+6DP7vZjJtiH3toHPc0bumhOy9R/ib8lnD5XX0DR8=",
        "fingerprint": {
          "rawId": 432126606,
          "currentIndex": 7,
          "deviceIndexes": [
            0,
            1,
            2,
            6,
            7
          ]
        },
        "timestamp": "1662538802754"
      },
      "AAAAAFG5": {
        "keyData": "yYXdZsyvZAwIkXHTob7t1SbnEMMkIAU+1SjIfJ031j8=",
        "fingerprint": {
          "rawId": 432126606,
          "currentIndex": 7,
          "deviceIndexes": [
            0,
            1,
            2,
            7
          ]
        },
        "timestamp": "1662538805459"
      }
    },
    "senderKeys": {
      "120363023934136490@g.us::6281398750388::0": [
        {
          "senderKeyId": 268831806,
          "senderChainKey": {
            "iteration": 54,
            "seed": "5A17F6wvqnWKthHtgjz5x40TsBIZAJEUVk2V/UGezlg="
          },
          "senderSigningKey": {
            "public": "BWPOxd6qOrAqxwXD2Z6v8HNss9Or5Bbs/M9yAStvSJ04"
          }
        }
      ],
      "120363044431898876@g.us::6289519595897::0": [
        {
          "senderKeyId": 1762619237,
          "senderChainKey": {
            "iteration": 3,
            "seed": "/wK8g/WJqug8Xk580s32PFof+yUmBZEyKYwA3yPJ49c="
          },
          "senderSigningKey": {
            "public": "BWA3gWGGOeBTeKVVWcfhR7yaFxrCIdstvkpQVH/VTNMF"
          }
        },
        {
          "senderKeyId": 1617075232,
          "senderChainKey": {
            "iteration": 1,
            "seed": "m9G/GxPCyGV1ztJxCMjeP51cIxRLhv17Y0e9TJ1k9pc="
          },
          "senderSigningKey": {
            "public": "BYVW6U1sVU2JUUeo6Lf9Hfftdr+b5vHJTpWclxttYLU+"
          }
        }
      ],
      "120363023934136490@g.us::6282331660134::0": [
        {
          "senderKeyId": 1014970019,
          "senderChainKey": {
            "iteration": 9,
            "seed": "GBPB6L7tIAInJfcww8seWJ59fpJUu2KNPXDvCokTJUc="
          },
          "senderSigningKey": {
            "public": "BVm43cJ6lpxhciC03oqSqAcMg4uTZCGhU5CwwkdJGXRm"
          }
        }
      ],
      "120363044431898876@g.us::62882007294963:2::0": [
        {
          "senderKeyId": 1069306740,
          "senderChainKey": {
            "iteration": 6,
            "seed": "rVuR26kHH73eCkUVxItUfCILDjQooabmjmiBiNr13fQ="
          },
          "senderSigningKey": {
            "public": "BSgoIi4hXzw2xDO4p6mmO4NrOSQLXyTFcTQXISf5YuZ7"
          }
        }
      ],
      "120363023934136490@g.us::6281334961360:46::0": [
        {
          "senderKeyId": 1556647279,
          "senderChainKey": {
            "iteration": 696,
            "seed": "IIXcYlI+NUwTOa1fkyJZJTMeDxjKD+f9Pk91Haqk3oI="
          },
          "senderSigningKey": {
            "public": "BVPIfK1Jb2bp5AnYK45UeifuNTSyl6jOojaRvyYp4lZ7"
          }
        }
      ]
    },
    "appStateVersions": {
      "critical_block": {
        "version": 8,
        "hash": {
          "type": "Buffer",
          "data": "xK0AeVyPN0bixt2UBJguwfKknfU4r5Dfe9lbDnGnM32/TkWzFhaKjFQCiF58hFA1TSNJJe7+CpEpy1z0bgs5vISUIos5ofFRxpfLGs7V0aDGR0yuIHI4JB7ixAYoKL7oup/+krit115Xc1z5hFzK4PkMyW5FW//NRhgga1VPuq8="
        },
        "indexValueMap": {
          "sr4r4EYTQw7AERMr696pYA53VwN7uAwrtpMOyFjGPY4=": {
            "valueMac": {
              "type": "Buffer",
              "data": "dyqI/v8nVTAD1tjo23rusDeWO1SAEtVzIMUuw5Lu0cE="
            }
          },
          "a+R+K6xYRlGkFCLu+gMADZDMZqCpkDVSv4/SBKQD6MQ=": {
            "valueMac": {
              "type": "Buffer",
              "data": "VDhpsw3Q4dkTZslAFMJbS9SlE7ioEqermzaxteCpFRk="
            }
          },
          "QRxIKqH76NMIGOskhL4mJEzF+HKDdQXjRZp1sy2tsyk=": {
            "valueMac": {
              "type": "Buffer",
              "data": "OI53TSgSRP9yxiAwDRw1n6Ckfbp7dP9+EcaZbHH5Mwo="
            }
          }
        }
      },
      "regular": {
        "version": 8,
        "hash": {
          "type": "Buffer",
          "data": "1Zg5rbfkaLARM3GhBjhjGWvuqfh1RSyrR7lpGC+Ci2InwL66aMXj7xJ0PsYRGd6H8ET1bG+VKeR+GNREhqFUcfTjBnFDbTAX2lchYig2vamk9T0pFkLKkZwaQxQlpKwvp6wUkjqyMKLeDHPBRPlnQtJhngY2qeH5R0s65fbpcWc="
        },
        "indexValueMap": {
          "FdUUiXfYbUyFTyvKLfj4g8057NLMQo/41IwCcL7CvJM=": {
            "valueMac": {
              "type": "Buffer",
              "data": "SqhSELvLPRPMoMeD0HnijeigRbR8EfzsgkDaliRB8Ig="
            }
          },
          "OhBnYDNi6soWrxMsWgY2FNsEZvL4BuyPaZvxqijOCMQ=": {
            "valueMac": {
              "type": "Buffer",
              "data": "oVJGJJ1k/vfwhC0ybboKT66D/jiKytSYurQrvWFd3aU="
            }
          },
          "X2L5fMG6aDkwy33W3D+r21vg0npt0ghxucz5ZJEY8xg=": {
            "valueMac": {
              "type": "Buffer",
              "data": "DjXBYBEySwIV6ScEtyKsFRnHJnvwu23dWZipc9IFjco="
            }
          },
          "dBBLpp4CZCc4QLJwI1Gr4CJPEYq75Hhe6j/3XIM0EAM=": {
            "valueMac": {
              "type": "Buffer",
              "data": "JUMaebRcWH1dQOdTUhcreeaRITwHBuFc4F2GvgotKTg="
            }
          },
          "hbbJ0Uzw8UYk5XPNHyf+zZMRLzzUsYYVK/zvC+EnCYU=": {
            "valueMac": {
              "type": "Buffer",
              "data": "ChdUIZ33F+gruBGAK3XGqx3S+hVNXRTdoVEjB2rjNOw="
            }
          },
          "pxOpHEbzqyCKy5B23rhhye1aUdi26C/4oEAg3a83U5c=": {
            "valueMac": {
              "type": "Buffer",
              "data": "JkvYLw1aEf21O1zRJzmKW89hEIQK+EmqE6KT2WJjbl8="
            }
          },
          "rxYPym+VH/AtkkU5xFCzxhjcA/JtRzhn7ju0h1DSvto=": {
            "valueMac": {
              "type": "Buffer",
              "data": "G/hBfdN5a5ehBGDGuOCN37dW/9OfSfDnbvcDI8qI0Oc="
            }
          },
          "II0rlpeYN0JD00LqNjuUjk/icIr+/GYQONI1UfS1/GA=": {
            "valueMac": {
              "type": "Buffer",
              "data": "bpPuCLBT7gLDeyDMUqt916MyVF89rYs8ko2upEnnRnk="
            }
          }
        }
      },
      "regular_high": {
        "version": 15,
        "hash": {
          "type": "Buffer",
          "data": "L5QF6p6ACxn04j/5nzoFWaZkCMB3y+edxRRIjJoWN8MNZn2lUC808r8sMt1L1WvpqCUKFIDtqdj4Gr0duPR/akTcvQMCgYddJFvVJG6xdfk/TMwGXntsmUvJh36vAgNaM576hC11CS7PUvZXtvHn/rZAr+4ClnEFd1nlVNiIL5c="
        },
        "indexValueMap": {
          "dM78+ce7KQW0XPSSkdIHBLSdMMK1sR6IQXQd2UQh0+8=": {
            "valueMac": {
              "type": "Buffer",
              "data": "T7bMQyB9vlX+FL/IfZBgdpxigT4ySR14bXb2uQ981+4="
            }
          },
          "uOc0n34ga5nANvlmcuJSNeYlcGkS08Hxca5Pj1eXWLs=": {
            "valueMac": {
              "type": "Buffer",
              "data": "5fCpC0/O2pca2cYngdolldEdRcgZST5KMRjfZTX9mno="
            }
          },
          "O42BXgKYc0syJhcnWVRGNBnUL6dKieWUaPjMPsswodA=": {
            "valueMac": {
              "type": "Buffer",
              "data": "zO6d1KsQm2kI8nw8V+DbksPL3BKeFQx+cgeYwm0VcYc="
            }
          },
          "wGtvyjVpsX/0SSKmLRpby+QX38psN2HveyLtEyiqhXw=": {
            "valueMac": {
              "type": "Buffer",
              "data": "vGhApwG/3FX0UjcuxlhVxr2cE+/ZUTm9f+EMEy4RthA="
            }
          },
          "ZddFmqV7kXHLj+AQQ/sZF53eI/O5IcqHuXO9KAr0BxI=": {
            "valueMac": {
              "type": "Buffer",
              "data": "T/R4HIXewOyoJR3NAghj+HaJBBQbk/wEduFXda3KMcM="
            }
          },
          "LSvDooECan6M+1FQLeshC63T3gQnUMbdvyqYaaXQ5bA=": {
            "valueMac": {
              "type": "Buffer",
              "data": "vlq+trHk6xooeFD9jiuoZbCtqouPAZvSFIcGx28VPU0="
            }
          },
          "ESLa1WCH3vxJMeBPLhrWrWj90C+jGJ4RvTFn/cyanzM=": {
            "valueMac": {
              "type": "Buffer",
              "data": "qcf55KM/3aolCWWPYa+b/iAaG248xEOqutDX3zCguDg="
            }
          },
          "3OiqK0l8/sQIYB/Zc4R/8Kw7z4Tui+oSa9vestzdfNA=": {
            "valueMac": {
              "type": "Buffer",
              "data": "++/i0Ep4XBAXjreInKnlXvdnGvSPk23npfy+6AEbge4="
            }
          },
          "KV2bSE2Kt5qf3Oy65R9Bq2XjV8P1UVGtOeghkIO/Yc0=": {
            "valueMac": {
              "type": "Buffer",
              "data": "UgAcRr4H/NlsMnZrJg31o01FpVbTccxXZlk0ECbKFQg="
            }
          }
        }
      },
      "regular_low": {
        "version": 8,
        "hash": {
          "type": "Buffer",
          "data": "B7XLpUDfPVwiqx9KKIbhS+oj2EjHe44CwwLLHrrzkqWjldPiY/zXAqRozFlNZQcTmhfT+DWUiRQtOCznpfmRnKBPV5EVotdiiXRkPaXEnAV54tpW4GWxLAYNDndu5KHc39hVto72aJicoTv8dOI7ULT6+Pd+ds/CT2WVik7ZzB4="
        },
        "indexValueMap": {
          "lr4EMl5L6qQWiqK9fee802Pu57HR9HzZyQgk61CYmzg=": {
            "valueMac": {
              "type": "Buffer",
              "data": "6OP/CFgZiTUgWQf9+PZKmWIkDaSs8OyDPipBGfrgWcQ="
            }
          },
          "XdjDdMwrQCQEtcmIOE3gxnHcRal05upc1MFSSU0jw90=": {
            "valueMac": {
              "type": "Buffer",
              "data": "mZgLMxZpI4VYjA7SjMMYPs9D1JsUYXOAmXgZdeRNKCE="
            }
          },
          "TKJpCdVlfx9FcvfZXlHxT7RMLtCgeXu4lFXDy1DrQ00=": {
            "valueMac": {
              "type": "Buffer",
              "data": "FFxuP/BD3hWJwFi/e2ZTpZaWMosbm/5v525N/7siyQo="
            }
          }
        }
      },
      "critical_unblock_low": {
        "version": 15,
        "hash": {
          "type": "Buffer",
          "data": "+92xWk7QnlYF7/T5vH8/GF4FIb8QJBan3/MRPzUjlP9rTshRWwIlohrCvGgJLW/kOGB3NrJMrw13L1arZ0DSjGPPZ7O0hpY34QEyUt9+E2RjuqGHt62aJItXEaEAYfe51dAlPJbhbDPZrkon0U50z8svfJbSav/7CNVfA6gex6U="
        },
        "indexValueMap": {
          "Bizn/Fj+kIaTYdi10HJCD8QcTqLlyRxqMhCQEznee/0=": {
            "valueMac": {
              "type": "Buffer",
              "data": "shEYvTUeIsM8ylY7diesXfNlMyZqCu9ELYJYAw30418="
            }
          },
          "Bp8Xl+Ug2GjyxhNlgalOU9ikIlRJa6DA801zK5nl8ts=": {
            "valueMac": {
              "type": "Buffer",
              "data": "VC6WgPpj/gk2zsunjC+AWY227tPeGkJoB1Bt19hS40Y="
            }
          },
          "EU5XWwPPKxWR0m/8XXgXpJhMhqeRfoXsD22+jcaQpuk=": {
            "valueMac": {
              "type": "Buffer",
              "data": "S8OfY9jLeIG/sv/qdFEg2cWFZ0YI+1ah9D4sENAZe/Q="
            }
          },
          "HAfjsORfZT/Ir3duUvK2172E2F7OtIQHS/Z3qiSaqLg=": {
            "valueMac": {
              "type": "Buffer",
              "data": "Uki9hCzJnzNAALvgeiKA9fT7BFVTDdB9OTbjdID/uH8="
            }
          },
          "HEUu7QSM4NZxFlDY53mhwDdTmliQgNg+UFI4YtI6Hd4=": {
            "valueMac": {
              "type": "Buffer",
              "data": "dx+fCcUrqqWhdEIIKL1k13imTu4yafii1094TGdT0Ww="
            }
          },
          "Hx7O6XQcG82AGsdvHbRm/WRjOnDRNinvv/zWnBkhk2o=": {
            "valueMac": {
              "type": "Buffer",
              "data": "PlM4H2f33kB14XEybEPL2YuaD7hRAJNHpEhMgNSMnEA="
            }
          },
          "H22ytLc6TB1wC5DKMegWvM3qoM19AfKsWqe/P9lIXDY=": {
            "valueMac": {
              "type": "Buffer",
              "data": "fn3C2pge/7kW/eP9WIdSyNFlm7PFFynLSLWMxf/pFKI="
            }
          },
          "Lp2r/82AuQkTOSbo+TFpnFuOIieTCQYAv/R1N4TbYAI=": {
            "valueMac": {
              "type": "Buffer",
              "data": "rK6Lro13k0Ra3UiMqPuuaWLLqADvpLjC259HshMe0cU="
            }
          },
          "LxYidmeANNbFPyqC6BjJXeB5AZCUeGHI0PSMGkO4OT8=": {
            "valueMac": {
              "type": "Buffer",
              "data": "xFd2lfViU2xaj/Ap/KRwr75jlkNVzBhoAqO14pGwN4A="
            }
          },
          "L4eUc2GY9VU0uObtpCFZ8+xP4tOnDbsFNrcHEkTdqWk=": {
            "valueMac": {
              "type": "Buffer",
              "data": "jUbzUIkO4qeYAGRXqRAt4k5jsUeSyTJYF/GmHtR/9Tw="
            }
          },
          "NKN2O/1ykbviRwolhVVMndgFFM7X8MZcM9pCTKywbn0=": {
            "valueMac": {
              "type": "Buffer",
              "data": "yB9z8XfQoytTurpn9XoVJvFh0iPXaNMpnxUtdCGO90Q="
            }
          },
          "NXX6KfkN6dNI6yZIwbqNP0/FyJyGZszTg9ztT5cNm1k=": {
            "valueMac": {
              "type": "Buffer",
              "data": "pc1w1c3rjUexUW+i7pNtbqw2vjtvBC35LuhIvXEoyEw="
            }
          },
          "R9pYYzyvbXx1aI9Miui0HoKSbUR4Gt1/u8F2JynpYfE=": {
            "valueMac": {
              "type": "Buffer",
              "data": "zFMokoawAMVRKDXG1T0xF1TGocRz+JGwT8f2p3J0HJY="
            }
          },
          "R/3iwnBALyt9PEE2aJc+T9kEwY/UBPct/WlU2J3G9aU=": {
            "valueMac": {
              "type": "Buffer",
              "data": "O7FmrE8nbyxHlkOceMFly/TDXJ/yVGtHwNZIKTW9wW4="
            }
          },
          "TIAFnZB5TDNgWygl7VSoUZDUUMap3/2yufLFs2wdpBQ=": {
            "valueMac": {
              "type": "Buffer",
              "data": "jwyBXW/CDZex2zECL28Y69UM2VOOEXKkoDCVyZWIM8I="
            }
          },
          "V8ObrpCUHd3MybeyWGP7KJsjYxQiI7I/S0fMNSeBmt8=": {
            "valueMac": {
              "type": "Buffer",
              "data": "IXdO3NZ+NNQIcEwtJtJvKofVpxIJqMYXJ38qfiKxGGA="
            }
          },
          "WGLQ2DrZR/zKksGC+bpUxobM0wKhmkHHM5yjTNtTuQc=": {
            "valueMac": {
              "type": "Buffer",
              "data": "kvg4+9zeQMhlMMdNYK/zHyVaYkKOPNRYtegpVHF5i2s="
            }
          },
          "Wkr8CdWS2dAp14MEklxREhtfwUb7d2UJYDqeQH35f7E=": {
            "valueMac": {
              "type": "Buffer",
              "data": "op83rWI9WFIio0hho74DvwcrRKWla3lFVXRN2VgLg94="
            }
          },
          "WoQ8+/gjyw9m9SWScT21pueDsbZah795pT5XI5L01fM=": {
            "valueMac": {
              "type": "Buffer",
              "data": "RxL+4lRlfWHiymL3TY2Uaza+9iGrX45jhE+Mb0qnqik="
            }
          },
          "aRjcJifm5dTpavwbMQowAQ6XQrbWmgVJVLPPsS+KMxY=": {
            "valueMac": {
              "type": "Buffer",
              "data": "6ZCM4RomWHaNhpcj/Cb+WWq6jkZLVXhoUmrz9KkZOJ4="
            }
          },
          "bJNGRQr+RUSaWNvXztqP2+3nfqc0bRxF3CSGsYleY7A=": {
            "valueMac": {
              "type": "Buffer",
              "data": "fBcKI9OWMNuqeU5wwEHGreRTwr2gMLyLmCbBhZvSLNY="
            }
          },
          "bc8hIMgiZInrjHU3vwn22GBfOn+waRAt99g7cMis7vw=": {
            "valueMac": {
              "type": "Buffer",
              "data": "iCLuJQ3Bj9fjxzAotN4EuwqmcYO/aynQhHyHTHjXaRk="
            }
          },
          "caG45o+ZSudVSDQVVLUf54yZRWmPixOlkeM9y1HaHDQ=": {
            "valueMac": {
              "type": "Buffer",
              "data": "Yl945lttv/58aSE5jkKyzzPV1nbXmmgwUux9O9g/4Ys="
            }
          },
          "cp/aJ0r+Qo/Jqo1vK8nZhZ3wW1dgTWwewu6De0Ecf9o=": {
            "valueMac": {
              "type": "Buffer",
              "data": "JxwfInRA5oGDBXqaEvd34redq7HVPJVYK5xRgX5ZRKY="
            }
          },
          "c+ahRpzsKhAEzfNH5iZkxGXZK7GiNKRGTt8OKnwaXW8=": {
            "valueMac": {
              "type": "Buffer",
              "data": "2g0M+QuCQ8Q4xPAAYeiNgg0mj59Kuj9yS/WUx+VSJYU="
            }
          },
          "gjykeQLcqIat59FTszy0WkXSTMa2PqjckwFhSiwCNLo=": {
            "valueMac": {
              "type": "Buffer",
              "data": "pU8wvoD+liqP+C1SLt/GfG8i4kEc/+eKouut1vslu7w="
            }
          },
          "of6KTMg/qCQBAZvKhU7cUfUgGrEOJJ90dTnTTLHBtvI=": {
            "valueMac": {
              "type": "Buffer",
              "data": "ypuhGXEX9aJ0S0OVvsBSfPEZiHY5IWxzA7R9VsUQs7s="
            }
          },
          "pHInG476J04pouGwlLQuXtk6TNdseU5WsivYLFei9kg=": {
            "valueMac": {
              "type": "Buffer",
              "data": "1FTpLKDYDkHcrui176ThE6+hlVRTkbn5ngA+P+FiI8Y="
            }
          },
          "pNNmnfTmcKljV2LUPCY98r4G6EY7o1EQg5sfBV/ELdg=": {
            "valueMac": {
              "type": "Buffer",
              "data": "zFqoZ3H2m3sbm30Jsc5fTwnU4j0Pa3Rc1VECduBaKNw="
            }
          },
          "p9Y9YUXcTbmUwQFy7ogb+D+gLFEERKHqVjMl1LxKsiE=": {
            "valueMac": {
              "type": "Buffer",
              "data": "ayU6Dnsnwqd1x/cpt+QBqem5CPdhX6FsjRsFeWDXtso="
            }
          },
          "rAtPCQ+P5An7EYbMav3YjfaKxyutUqpwZE+AW6UbpE0=": {
            "valueMac": {
              "type": "Buffer",
              "data": "cmB1uwXKgCrV94+7YJlpUJhEYgYN8iy59Q6JtgJfMlE="
            }
          },
          "spqlOxxQRwboy28rPinvTyXx2t4YNPB0FsXl4sZmmg4=": {
            "valueMac": {
              "type": "Buffer",
              "data": "lThRT55CCPUgs5YRjmCAXSQHg0STpi51Kr0OUAuq6ME="
            }
          },
          "tgQqJLnz+9KdQJ3H2UFrf6//hdNFPdfcCbe+CJ6hr7c=": {
            "valueMac": {
              "type": "Buffer",
              "data": "n/zs+0b3Q+0NjFoYE2vfL9qKmjiIHKKo13ugqk0c92Q="
            }
          },
          "wW/CZ7qixDh5gu1wnAlsVZZkB4RKZrX9/UmRd2aJHts=": {
            "valueMac": {
              "type": "Buffer",
              "data": "Ni6YFi/pLzz41tv4snIYLPucTPLfZVAHp08YvEgxYFo="
            }
          },
          "xGqK7D4FvIvt1K5KQK3ucJIE2trUqXCBrbCXzMsLcXY=": {
            "valueMac": {
              "type": "Buffer",
              "data": "+GJ3nR4oUJRZ40dUkJCdyaI6lFGx6zXX5UryHr6H9mQ="
            }
          },
          "xL2A1CvH5t1+SFb6R6cSppJKrVHijlWHVs9vZGkvDbo=": {
            "valueMac": {
              "type": "Buffer",
              "data": "Cd+md2qm1FfF429MB7ca+Kd0IRKIpy6HPYLIpNqcDqM="
            }
          },
          "xb9Tntu1dn5hkBLu1Tkn0WvEB1HC8CxKkon6FydkotM=": {
            "valueMac": {
              "type": "Buffer",
              "data": "gVPWr26AwZKn9P3VBtXCDSwAfXFMcWaqnjiyRwypdMQ="
            }
          },
          "z2QxO/d9N3nfxxlL0xrK+3760MmMP8yH8IysZBREm9w=": {
            "valueMac": {
              "type": "Buffer",
              "data": "b6Et2p8XockBRRWH5yckw0K0Gqzwmw2J1Xzb2FsvfuU="
            }
          },
          "1pXwaeMBZ4CkwucwwGTgqncVeAGLFvhOoAHP9DTHMtA=": {
            "valueMac": {
              "type": "Buffer",
              "data": "ScrDotTkk0MUh9QukUcvz4Ue3BwFVCUHmaLrPxRuq/k="
            }
          },
          "6Ye0pmzGOtVFm8BeaF9aCdT9t6pD6xVjv+eCHCQeaa4=": {
            "valueMac": {
              "type": "Buffer",
              "data": "lzOOu4/HtTmrWD7B3w3iDyMCBEh7E5rXHvAaBrwt9cU="
            }
          },
          "6zwkFbXJsUxAz2fiC0MY3KzYLXAhUuEuyoicJapJc8o=": {
            "valueMac": {
              "type": "Buffer",
              "data": "jY8pfhNbz/7djg1uq9IiTFxijt90tVu2GA9l+iIBRBg="
            }
          },
          "8uOBzVdwmL7ggty9UVqBq0ZUHE4zq1XhfAuZGBDga6I=": {
            "valueMac": {
              "type": "Buffer",
              "data": "sIRZSCGea9EyljjncdKXv1ltqNxyxXAmNbmd7woIT3w="
            }
          },
          "9iRocrN2SMDFUUrFTzTWr0CVEAFJ3Xxx6i3I9dHZZhs=": {
            "valueMac": {
              "type": "Buffer",
              "data": "7GE2OBiPCC/HxJ5vSIeagOT7P2qOVSR3iRy0TadaARk="
            }
          },
          "9qUgiVZ3LPedHNsRQwT29lbznTxoDLvfwqT1gQlzmBU=": {
            "valueMac": {
              "type": "Buffer",
              "data": "latjWl7MLViXKWmz1/2aYuIuDLmrMU3Re26171UEAVM="
            }
          },
          "+IaRWq/rv8C0YQ60m6CZwrNDf8BRspxPsJzu1OkMbRY=": {
            "valueMac": {
              "type": "Buffer",
              "data": "xDXDTB5NoJkw1FyhX+6ENxUl1nDB9Q2zz4jPO8bpqMU="
            }
          },
          "+IyhnuwKHzJ7tU7HNCyI+qGXtTt7hgrRCB4KXPDdsg0=": {
            "valueMac": {
              "type": "Buffer",
              "data": "tUo17wlbjvBU9GzTjFo95YWnPTl9TlYxf9yIx5rvXqU="
            }
          },
          "7hglkklxEevHbz2gs41B7RUE+DasIxJputDDiY7a97Q=": {
            "valueMac": {
              "type": "Buffer",
              "data": "tYgPF+JGoQVz0pplJ9Lt8vE3/WslXtYPqEoHyMwz1mc="
            }
          },
          "9iYgvFrKlkMg1q4sa/MocSTkY0zdtIUBa+dv2O0wNWM=": {
            "valueMac": {
              "type": "Buffer",
              "data": "3DUd186qW7raBPfN6xucFFt+qof65bMNi3Mz92EfP6g="
            }
          },
          "ds4daxyp9t0t5WFS/ch4BM6akhg9TSu8OHXMGvqqe0E=": {
            "valueMac": {
              "type": "Buffer",
              "data": "Kw8p7HAwldw8stjMEOiylzsO16P9lQclJYA2Bd+KSm0="
            }
          },
          "rfvbflFQNrzhEpWomvX7UbwYNRUVoqX+lNKim2p+cEM=": {
            "valueMac": {
              "type": "Buffer",
              "data": "xvqWSmjafP/sDe7WyQS94W0HVckz/wi8Z8f35Mqe1vA="
            }
          },
          "JVk5zmei8A0ZLbULGD8ibNhgmdxMaq0JqJ/QgP/qijY=": {
            "valueMac": {
              "type": "Buffer",
              "data": "vtGCzJJrLGhRMKEDr2FWxy13PLW8V0Zf3ynO5TS9a40="
            }
          },
          "agwd4DilWLGKx/lYGGSQ4oVQKZFTe+GyoFZtwHtzlhw=": {
            "valueMac": {
              "type": "Buffer",
              "data": "2PxM1oMCKy5t7j32NnNygjIDFgoXPbigGm5/uC/uGWc="
            }
          },
          "vYQi0Qej7bmtR24MfNmlAKmqHBE7S+whPIbROOtQT+A=": {
            "valueMac": {
              "type": "Buffer",
              "data": "YdvAHw8iWr/ILmxlDUZkM+6Z6z+qh2jKybHLC/zJidw="
            }
          }
        }
      }
    }
  }
}
